<?xml version="1.0" encoding="utf-8" ?>
<dwsync>
<file name="form.js" server="webltga.espe.edu.ec//var/www/html/sg-ecp/sg-ecp/" local="129648492580000000" remote="129914066870000000" />
<file name="grid.js" server="webltga.espe.edu.ec//var/www/html/sg-ecp/sg-ecp/" local="129648495620000000" remote="129914066870000000" />
<file name="store.js" server="webltga.espe.edu.ec//var/www/html/sg-ecp/sg-ecp/" local="129648454760000000" remote="129914066870000000" />
<file name="form.js" server="webltga.espe.edu.ec//var/www/html/sg-ecp/" local="129648492580000000" remote="129996298440000000" />
<file name="grid.js" server="webltga.espe.edu.ec//var/www/html/sg-ecp/" local="129648495620000000" remote="129996298440000000" />
<file name="store.js" server="webltga.espe.edu.ec//var/www/html/sg-ecp/" local="129648454760000000" remote="129996298440000000" />
<file name="form.js" server="webltga.espe.edu.ec//var/www/html/sg-proyectos/" local="129648492580000000" remote="130149385630000000" />
<file name="grid.js" server="webltga.espe.edu.ec//var/www/html/sg-proyectos/" local="129648495620000000" remote="130149385630000000" />
<file name="store.js" server="webltga.espe.edu.ec//var/www/html/sg-proyectos/" local="129648454760000000" remote="130149385630000000" />
</dwsync>